cpu/IMem.v
module IMem(    o_instruction, 
                i_pc);

    input wire[31:0] i_pc;
    output wire[31:0] o_instruction;

    parameter numInstructions = 11;
    parameter filepath = "../tests/rtest/txt/rtest.txt";
    reg[31:0] instruction_arr [0:numInstructions-1];

    
    //Filepath to assembled data
    initial $readmemh(filepath, instruction_arr);
    assign o_instruction = instruction_arr[i_pc];

endmodule

cpu/testbench/IMem_tb.v
module IMem_tb();

    reg[31:0]   pc;

    wire[31:0]  instruction;

    IMem  #(.filepath("../tests/assembled/rtest.o"), .numInstructions(11)) 
            imem(  .o_instruction(instruction),
                    .i_pc(pc));

    initial begin
        
        # 1
        pc = 0;

        # 1
        pc = 2;

        # 1
        pc = 3;

        # 1
        pc = 4;

        # 1
        pc = 5;

        # 1
        pc = 6;

        # 1
        pc = 7;

        # 1
        pc = 8;

        # 1
        pc = 9;

        # 1
        pc = 10;

        # 1
        
        $finish;
    end

    initial
    begin
        $dumpfile("imem.vcd");
        $dumpvars(0, IMem_tb);
    end

endmodule

cpu/imem.vcd
$date
	Thu May  4 09:46:35 2023
$end
$version
	Icarus Verilog
$end
$timescale
	1s
$end
$scope module IMem_tb $end
$var wire 32 ! instruction [31:0] $end
$var reg 32 " pc [31:0] $end
$scope module imem $end
$var wire 32 # i_pc [31:0] $end
$var wire 32 $ o_instruction [31:0] $end
$upscope $end
$upscope $end
$enddefinitions $end
#0
$dumpvars
bx $
bx #
bx "
bx !
$end
#1
b1100010000000100010011 !
b1100010000000100010011 $
b0 "
b0 #
#2
b1100010000000010110011 !
b1100010000000010110011 $
b10 "
b10 #
#3
b1000000001100010000000010110011 !
b1000000001100010000000010110011 $
b11 "
b11 #
#4
b1100010100000010110011 !
b1100010100000010110011 $
b100 "
b100 #
#5
b1100010110000010110011 !
b1100010110000010110011 $
b101 "
b101 #
#6
b1100010111000010110011 !
b1100010111000010110011 $
b110 "
b110 #
#7
b1100010001000010110011 !
b1100010001000010110011 $
b111 "
b111 #
#8
b1100010101000010110011 !
b1100010101000010110011 $
b1000 "
b1000 #
#9
b1000000001100010101000010110011 !
b1000000001100010101000010110011 $
b1001 "
b1001 #
#10
b1100010011000010110011 !
b1100010011000010110011 $
b1010 "
b1010 #
