cpu/ALU.v
module ALU( o_result, 
            o_zero, 
            o_neg, 
            i_operand1, 
            i_operand2, 
            i_ALUControl);

    output  reg[31:0]  o_result;
    output  reg        o_zero, 
                        o_neg;

    input   wire[31:0]  i_operand1, 
                        i_operand2;
    input   wire [3:0]  i_ALUControl;

    always @(*)
    begin 
        case(i_ALUControl) //Seems like way few cases for an ALU
            4'b0000 : o_result = i_operand1 & i_operand2; //0
            4'b0001 : o_result = i_operand1 | i_operand2; //1
            4'b0010 : o_result = i_operand1 + i_operand2; //2
            4'b0011 : o_result = i_operand1 ^ i_operand2; //added //3
            4'b0110 : o_result = i_operand1 - i_operand2; //6
            4'b1000 : o_result = i_operand1 << i_operand2; //added //8
            4'b1001 : o_result = i_operand1 >> i_operand2; //added //9
            4'b1010 : o_result = i_operand1 >>> i_operand2; //added //10

        endcase;
        o_zero = o_result === 0;
        o_neg = o_result < 0;
    end
endmodule

cpu/testbench/ALU_tb.v
module ALU_tb();

    reg[31:0]   op1, 
                op2;
    reg [3:0]   ctl;

    wire        zero, 
                neg;

    wire[31:0]  result;

    ALU alu(
        .o_result(result),
        .o_zero(zero),
        .o_neg(neg),
        .i_operand1(op1),
        .i_operand2(op2),
        .i_ALUControl(ctl)
    );

    initial begin
        // Test case 1 - AND operation
        op1 = 32'hAAAAAAAA;
        op2 = 32'h55555555;
        ctl = 4'b0000;
        
        

        // Test case 2 - OR operation
        # 10 op1 = 32'hAAAAAAAA;
        op2 = 32'h55555555;
        ctl = 4'b0001;
        
        

        // Test case 3 - ADD operation
        # 10 op1 = 10;
        op2 = 20;
        ctl = 4'b0010;
        

        // Test case 4 - XOR operation
        # 10 op1 = 32'hAAAAAAAA;
        op2 = 32'h55555555;
        ctl = 4'b0011;
        

        // Test case 5 - SUB operation
        # 10 op1 = 20;
        op2 = 10;
        ctl = 4'b0110;
        

        // Test case 6 - SHL operation
        # 10 op1 = 16'h0001;
        op2 = 4;
        ctl = 4'b1000;
        

        // Test case 7 - SHR operation
        # 10 op1 = 16'h8000;
        op2 = 4;
        ctl = 4'b1001;
        

        // Test case 8 - SRA operation
        # 10 op1 = -16;
        op2 = 1;
        ctl = 4'b1010;
        
        # 10

        $finish;
    end

     initial
    begin
        $dumpfile("alu.vcd");
        $dumpvars(0, ALU_tb);
    end

endmodule

cpu/testbench/alu.vcd
$date
	Thu May  4 00:22:35 2023
$end
$version
	Icarus Verilog
$end
$timescale
	1s
$end
$scope module ALU_tb $end
$var wire 1 ! zero $end
$var wire 32 " result [31:0] $end
$var wire 1 # neg $end
$var reg 4 $ ctl [3:0] $end
$var reg 32 % op1 [31:0] $end
$var reg 32 & op2 [31:0] $end
$scope module alu $end
$var wire 4 ' i_ALUControl [3:0] $end
$var wire 32 ( i_operand1 [31:0] $end
$var wire 32 ) i_operand2 [31:0] $end
$var reg 1 # o_neg $end
$var reg 32 * o_result [31:0] $end
$var reg 1 ! o_zero $end
$upscope $end
$upscope $end
$enddefinitions $end
#0
$dumpvars
b0 *
b1010101010101010101010101010101 )
b10101010101010101010101010101010 (
b0 '
b1010101010101010101010101010101 &
b10101010101010101010101010101010 %
b0 $
0#
b0 "
1!
$end
#10
0!
b11111111111111111111111111111111 "
b11111111111111111111111111111111 *
b1 $
b1 '
#20
b11110 "
b11110 *
b10 $
b10 '
b10100 &
b10100 )
b1010 %
b1010 (
#30
b11111111111111111111111111111111 "
b11111111111111111111111111111111 *
b11 $
b11 '
b1010101010101010101010101010101 &
b1010101010101010101010101010101 )
b10101010101010101010101010101010 %
b10101010101010101010101010101010 (
#40
b1010 "
b1010 *
b110 $
b110 '
b1010 &
b1010 )
b10100 %
b10100 (
#50
b10000 "
b10000 *
b1000 $
b1000 '
b100 &
b100 )
b1 %
b1 (
#60
b100000000000 "
b100000000000 *
b1001 $
b1001 '
b1000000000000000 %
b1000000000000000 (
#70
b1111111111111111111111111111000 "
b1111111111111111111111111111000 *
b1010 $
b1010 '
b1 &
b1 )
b11111111111111111111111111110000 %
b11111111111111111111111111110000 (
