cpu/ControlSignals.v
module ControlSignals(  o_ALUSrc, 
                        o_MemtoReg,
                        o_RegWrite,
                        o_MemRead,
                        o_MemWrite,
                        o_Branch,
                        o_ALUOp,
                        o_ImmSrc,
                        i_opcode);

    output  reg o_ALUSrc, 
                o_MemtoReg,
                o_RegWrite,
                o_MemRead,
                o_MemWrite,
                o_Branch;
    output  reg[2:0]o_ImmSrc;
    output  reg[1:0] o_ALUOp;
    
    input   wire[6:0]    i_opcode;

    always @(*)
    begin
        case(i_opcode)
            7'b0110011: 
                begin
                    o_ALUSrc = 0;
                    o_MemtoReg = 0;
                    o_RegWrite = 1;
                    o_MemRead = 0;
                    o_MemWrite = 0;
                    o_Branch = 0;
                    o_ALUOp = 2'b10;
                    o_ImmSrc = 0;
                end//R Format
            7'b0010011: 
                begin
                    o_ALUSrc = 1;
                    o_MemtoReg = 0;
                    o_RegWrite = 1;
                    o_MemRead = 0;
                    o_MemWrite = 0;
                    o_Branch = 0;
                    o_ALUOp = 2'b10; //????
                    o_ImmSrc = 1;
                end//I arithmetic Format
            7'b0000011: 
                begin
                    o_ALUSrc = 1;
                    o_MemtoReg = 1;
                    o_RegWrite = 1;
                    o_MemRead = 1;
                    o_MemWrite = 0;
                    o_Branch = 0;
                    o_ALUOp = 2'b00;
                    o_ImmSrc = 1;
                end//I load Format
            7'b0100011: 
                begin
                    o_ALUSrc = 1;
                    o_MemtoReg = 0; //x
                    o_RegWrite = 0;
                    o_MemRead = 0;
                    o_MemWrite = 1;
                    o_Branch = 0;
                    o_ALUOp = 2'b00;
                    o_ImmSrc = 2;
                end//S Format
            7'b1100011: 
                begin
                    o_ALUSrc = 0;
                    o_MemtoReg = 0; //x
                    o_RegWrite = 0;
                    o_MemRead = 0;
                    o_MemWrite = 0;
                    o_Branch = 1;
                    o_ALUOp = 2'b01;
                    o_ImmSrc = 3;
                end//B Format
            7'b1101111: 
                begin
                    o_ALUSrc = 0;   
                    o_MemtoReg = 0; //x
                    o_RegWrite = 1;
                    o_MemRead = 0;
                    o_MemWrite = 0;
                    o_Branch = 0;
                    o_ALUOp = 2'b01; 
                    o_ImmSrc = 4;
                end//JAL
            7'b1100111: 
                begin
                    o_ALUSrc = 0;
                    o_MemtoReg = 0; 
                    o_RegWrite = 1;
                    o_MemRead = 0;
                    o_MemWrite = 0;
                    o_Branch = 1;
                    o_ALUOp = 2'b0;
                    o_ImmSrc = 1;
                end//JALR
            7'b0010111: 
                begin
                    o_ALUSrc = 0;
                    o_MemtoReg = 0; 
                    o_RegWrite = 1;
                    o_MemRead = 0;
                    o_MemWrite = 0;
                    o_Branch = 1;
                    o_ALUOp = 2'b0; 
                    o_ImmSrc = 5;
                end//U Format
                //Not supporting I* format, I don't have a system to call on
        endcase 
    end

    
endmodule

cpu/testbench/ControlSignals_tb.v
module ControlSignals_tb();

    reg[6:0]   opcode;

    wire    ALUSrc,
            MemToReg,
            RegWrite,
            MemRead,
            MemWrite,
            Branch;
    
    wire[1:0]   ALUOp;
    wire[2:0]   ImmSrc;

   ControlSignals cs(  .o_ALUSrc(ALUSrc), 
                        .o_MemtoReg(MemToReg),
                        .o_RegWrite(RegWrite),
                        .o_MemRead(MemRead),
                        .o_MemWrite(MemWrite),
                        .o_Branch(Branch),
                        .o_ALUOp(ALUOp),
                        .o_ImmSrc(ImmSrc),
                        .i_opcode(opcode));

    initial begin
        # 10
        // Test case 1 - R Format
        opcode = 7'b0110011;

        # 10
        // Test case 2 - I Format Arithmetic
        opcode = 7'b0010011;

        # 10
        // Test case 3 - I Format Load
        opcode = 7'b0000011;

        # 10
        // Test case 4 - S Format
        opcode = 7'b0100011;

        # 10
        // Test case 5 - B Format
        opcode = 7'b1100011;

        # 10
        // Test case 6 - JAL Instruction
        opcode = 7'b1101111;

        # 10
        // Test case 7 - JALR Instruction
        opcode = 7'b1100111;

        # 10
        // Test case 8 - U Format
        opcode = 7'b0010111;

        # 10
        $finish;
    end

     initial
    begin
        $dumpfile("controlsignals.vcd");
        $dumpvars(0, ControlSignals_tb);
    end

endmodule

cpu/testbench/controlsignals.vcd
$date
	Thu May  4 00:55:39 2023
$end
$version
	Icarus Verilog
$end
$timescale
	1s
$end
$scope module ControlSignals_tb $end
$var wire 1 ! RegWrite $end
$var wire 1 " MemWrite $end
$var wire 1 # MemToReg $end
$var wire 1 $ MemRead $end
$var wire 3 % ImmSrc [2:0] $end
$var wire 1 & Branch $end
$var wire 1 ' ALUSrc $end
$var wire 2 ( ALUOp [1:0] $end
$var reg 7 ) opcode [6:0] $end
$scope module cs $end
$var wire 7 * i_opcode [6:0] $end
$var reg 2 + o_ALUOp [1:0] $end
$var reg 1 ' o_ALUSrc $end
$var reg 1 & o_Branch $end
$var reg 3 , o_ImmSrc [2:0] $end
$var reg 1 $ o_MemRead $end
$var reg 1 " o_MemWrite $end
$var reg 1 # o_MemtoReg $end
$var reg 1 ! o_RegWrite $end
$upscope $end
$upscope $end
$enddefinitions $end
#0
$dumpvars
bx ,
bx +
bx *
bx )
bx (
x'
x&
bx %
x$
x#
x"
x!
$end
#10
b0 %
b0 ,
b10 (
b10 +
0&
0"
0$
1!
0#
0'
b110011 )
b110011 *
#20
b1 %
b1 ,
1'
b10011 )
b10011 *
#30
b0 (
b0 +
1$
1#
b11 )
b11 *
#40
b10 %
b10 ,
1"
0$
0!
0#
b100011 )
b100011 *
#50
b11 %
b11 ,
b1 (
b1 +
1&
0"
0'
b1100011 )
b1100011 *
#60
b100 %
b100 ,
0&
1!
b1101111 )
b1101111 *
#70
b101 %
b101 ,
b0 (
b0 +
1&
b1100111 )
b1100111 *
#80
b110 %
b110 ,
b10111 )
b10111 *
